dataproc_utility_tools/__init__.py
dataproc_utility_tools/clean_dataset.py
dataproc_utility_tools/cli.py
dataproc_utility_tools/schema_analyzer.py
dataproc_utility_tools/utils.py
dataproc_utility_tools-0.1.0.dist-info/METADATA
dataproc_utility_tools-0.1.0.dist-info/WHEEL
dataproc_utility_tools-0.1.0.dist-info/entry_points.txt
dataproc_utility_tools-0.1.0.dist-info/top_level.txt
dataproc_utility_tools-0.1.0.dist-info/RECORD
