Metadata-Version: 2.4
Name: dataproc-utility-tools
Version: 0.1.0
Summary: Dataproc Utility Tools - A comprehensive toolkit for data quality analysis, schema validation, and dataset cleaning with PySpark integration
Author-email: Rodrigo Ribeiro <rodrigo.s.ribeiro98@gmail.com>
Project-URL: Homepage, https://github.com/rodrigo-sr/dataproc_utility_tools
Project-URL: Repository, https://github.com/rodrigo-sr/dataproc_utility_tools
Requires-Python: >=3.10
Requires-Dist: pandas>=2.1.0
Requires-Dist: numpy>=2.1.0
Provides-Extra: dev
Requires-Dist: pytest>=6.0; extra == "dev"
Requires-Dist: ruff>=0.1.0; extra == "dev"
